arms/__init__.py
arms/__main__.py
arms/main.py
arms/utils/__init__.py
arms/utils/common.py
arms/utils/wordstyle.py
arms-2.1.0.dist-info/METADATA
arms-2.1.0.dist-info/WHEEL
arms-2.1.0.dist-info/entry_points.txt
arms-2.1.0.dist-info/top_level.txt
arms-2.1.0.dist-info/RECORD
