Metadata-Version: 2.4
Name: arms
Version: 2.1.0
Summary: Archive and Replacement Management System - A markdown-based file archive utility with intelligent text replacement
Home-page: https://pypi.python.org/pypi/arms
Author: qorzj
Author-email: inull@qq.com
License: MIT
Keywords: archive markdown replacement template packaging distribution
Platform: any
Classifier: Development Status :: 4 - Beta
Classifier: Intended Audience :: Developers
Classifier: License :: OSI Approved :: MIT License
Classifier: Programming Language :: Python :: 3
Classifier: Programming Language :: Python :: 3.7
Classifier: Programming Language :: Python :: 3.8
Classifier: Programming Language :: Python :: 3.9
Classifier: Programming Language :: Python :: 3.10
Classifier: Programming Language :: Python :: 3.11
Classifier: Topic :: Software Development :: Build Tools
Classifier: Topic :: System :: Archiving
Classifier: Topic :: Text Processing :: Markup :: Markdown
Requires-Dist: lesscli>=0.2.0
Dynamic: author
Dynamic: author-email
Dynamic: classifier
Dynamic: description
Dynamic: description-content-type
Dynamic: home-page
Dynamic: keywords
Dynamic: license
Dynamic: platform
Dynamic: requires-dist
Dynamic: summary
